opportunity_core/__init__.py
opportunity_core/batch/__init__.py
opportunity_core/batch/opportunity_paapi/__init__.py
opportunity_core/batch/opportunity_paapi/price_history_monitor.py
opportunity_core/config/__init__.py
opportunity_core/models/__init__.py
opportunity_core/models/database.py
opportunity_core/scripts/__init__.py
opportunity_core/scripts/init_database.py
opportunity_core/services/__init__.py
opportunity_core/services/database_manager.py
opportunity_core/services/deal_detection.py
opportunity_core/services/price_monitoring.py
opportunity_core/services/product_discovery.py
opportunity_core/utils/__init__.py
opportunity_core/utils/api_helper.py
opportunity_core/utils/authentication.py
opportunity_core/utils/comment_generator.py
opportunity_core/utils/load_config.py
opportunity_core/utils/telegram_notifier.py
opportunity_core/utils/twitter_notifier.py
paapi5_python_sdk/__init__.py
paapi5_python_sdk/api_client.py
paapi5_python_sdk/configuration.py
paapi5_python_sdk/rest.py
paapi5_python_sdk/api/__init__.py
paapi5_python_sdk/api/default_api.py
paapi5_python_sdk/auth/__init__.py
paapi5_python_sdk/auth/sign_helper.py
paapi5_python_sdk/models/__init__.py
paapi5_python_sdk/models/availability.py
paapi5_python_sdk/models/big_decimal.py
paapi5_python_sdk/models/browse_node.py
paapi5_python_sdk/models/browse_node_ancestor.py
paapi5_python_sdk/models/browse_node_child.py
paapi5_python_sdk/models/browse_node_info.py
paapi5_python_sdk/models/browse_nodes_result.py
paapi5_python_sdk/models/by_line_info.py
paapi5_python_sdk/models/classifications.py
paapi5_python_sdk/models/condition.py
paapi5_python_sdk/models/content_info.py
paapi5_python_sdk/models/content_rating.py
paapi5_python_sdk/models/contributor.py
paapi5_python_sdk/models/customer_reviews.py
paapi5_python_sdk/models/deal_details.py
paapi5_python_sdk/models/delivery_flag.py
paapi5_python_sdk/models/dimension_based_attribute.py
paapi5_python_sdk/models/duration_price.py
paapi5_python_sdk/models/error_data.py
opportunity_core-0.1.0.dist-info/METADATA
opportunity_core-0.1.0.dist-info/WHEEL
opportunity_core-0.1.0.dist-info/top_level.txt
opportunity_core-0.1.0.dist-info/RECORD
