Metadata-Version: 2.4
Name: opportunity-core
Version: 0.1.0
Summary: Core library for Opportunity Radar - Shared utilities and services
Author: Mustafa Aykon
Author-email: Mustafa Aykon <mustafaaykon@users.noreply.github.com>
License: MIT
Project-URL: Homepage, https://github.com/mustafaaykon/opportunity-radar
Project-URL: Repository, https://github.com/mustafaaykon/opportunity-radar.git
Project-URL: Issues, https://github.com/mustafaaykon/opportunity-radar/issues
Keywords: opportunity,radar,deals,amazon,monitoring
Classifier: Development Status :: 3 - Alpha
Classifier: Intended Audience :: Developers
Classifier: License :: OSI Approved :: MIT License
Classifier: Programming Language :: Python :: 3
Classifier: Programming Language :: Python :: 3.11
Requires-Python: >=3.11
Requires-Dist: requests>=2.31.0
Requires-Dist: python-dotenv>=1.0.0
Requires-Dist: loguru>=0.7.0
Requires-Dist: tweepy>=4.14.0
Requires-Dist: pydantic>=2.12.4
Requires-Dist: pydantic-settings>=2.12.0
Requires-Dist: python-telegram-bot>=22.5
Requires-Dist: six>=1.16.0
Requires-Dist: urllib3>=1.26.0
Requires-Dist: certifi>=2023.7.22
Requires-Dist: python-dateutil>=2.9.0
Requires-Dist: sqlalchemy>=2.0.0
Requires-Dist: psycopg2-binary>=2.9.0
Provides-Extra: dev
Requires-Dist: pytest>=7.0.0; extra == "dev"
Requires-Dist: pytest-cov>=4.0.0; extra == "dev"
Requires-Dist: black>=23.0.0; extra == "dev"
Requires-Dist: ruff>=0.1.0; extra == "dev"
Dynamic: author
Dynamic: requires-python
